autom8it/__init__.py
autom8it/aws.py
autom8it/logger.py
autom8it-1.2.2.dist-info/METADATA
autom8it-1.2.2.dist-info/WHEEL
autom8it-1.2.2.dist-info/top_level.txt
autom8it-1.2.2.dist-info/RECORD
