Metadata-Version: 2.1
Name: autom8it
Version: 1.2.2
Summary: Automate IT operations
Home-page: https://github.com/eldad1221/autom8it
Author: Eldad Bishari
Author-email: eldad@1221tlv.org
Classifier: Programming Language :: Python :: 3
Classifier: License :: OSI Approved :: MIT License
Classifier: Operating System :: OS Independent
Requires-Python: >=3.7
Requires-Dist: PyYAML (==6.0)
Requires-Dist: pytz (==2021.3)
Requires-Dist: cerberus (==1.3.4)
Requires-Dist: boto3 (==1.26.3)
Requires-Dist: requests (==2.28.1)
